filter_stations/__init__.py
filter_stations/datasets_loader.py
filter_stations/filter_stations.py
filter_stations/kieni_data_access.py
filter_stations/geo/gadm41_KEN_0.cpg
filter_stations/geo/gadm41_KEN_0.dbf
filter_stations/geo/gadm41_KEN_0.prj
filter_stations/geo/gadm41_KEN_0.shp
filter_stations/geo/gadm41_KEN_0.shx
filter_stations/geo/gadm41_KEN_1.cpg
filter_stations/geo/gadm41_KEN_1.dbf
filter_stations/geo/gadm41_KEN_1.prj
filter_stations/geo/gadm41_KEN_1.shp
filter_stations/geo/gadm41_KEN_1.shx
filter_stations/geo/gadm41_KEN_2.cpg
filter_stations/geo/gadm41_KEN_2.dbf
filter_stations/geo/gadm41_KEN_2.prj
filter_stations/geo/gadm41_KEN_2.shp
filter_stations/geo/gadm41_KEN_2.shx
filter_stations/geo/gadm41_KEN_3.cpg
filter_stations/geo/gadm41_KEN_3.dbf
filter_stations/geo/gadm41_KEN_3.json
filter_stations/geo/gadm41_KEN_3.prj
filter_stations/geo/gadm41_KEN_3.shp
filter_stations/geo/gadm41_KEN_3.shx
filter_stations-0.7.1.dist-info/METADATA
filter_stations-0.7.1.dist-info/WHEEL
filter_stations-0.7.1.dist-info/entry_points.txt
filter_stations-0.7.1.dist-info/top_level.txt
filter_stations-0.7.1.dist-info/RECORD
