Metadata-Version: 2.4
Name: filter_stations
Version: 0.7.1
Summary: Making it easier to navigate and clean TAHMO weather station data and creating a way to access our unified weather dataset to reduce data fragmentation and global data divide in Africa.
Home-page: https://github.com/kaburia/filter-stations
Author: Austin Kaburia
Author-email: kaburiaaustin1@gmail.com
Requires-Dist: numpy
Requires-Dist: pandas
Requires-Dist: xarray
Requires-Dist: rioxarray
Requires-Dist: rasterio
Requires-Dist: huggingface_hub
Requires-Dist: requests
Requires-Dist: python-dateutil
Requires-Dist: tqdm
Requires-Dist: haversine
Requires-Dist: networkx
Requires-Dist: dask
Requires-Dist: zarr
Dynamic: author
Dynamic: author-email
Dynamic: description
Dynamic: description-content-type
Dynamic: home-page
Dynamic: requires-dist
Dynamic: summary
